LICENSE
MANIFEST.in
README.rst
requirements.txt
setup.cfg
setup.py
ckanext/__init__.py
ckanext/metadata/__init__.py
ckanext/metadata/plugin.py
ckanext/metadata/templates/package/snippets/additional_info.html
ckanext/metadata/templates/package/snippets/package_basic_fields.html
ckanext/metadata/templates/package/snippets/package_metadata_fields.html
ckanext/metadata/templates/package/snippets/resource_form.html
ckanext/metadata/tests/__init__.py
ckanext/metadata/tests/test_plugin.py
ckanext_metadata.egg-info/PKG-INFO
ckanext_metadata.egg-info/SOURCES.txt
ckanext_metadata.egg-info/dependency_links.txt
ckanext_metadata.egg-info/entry_points.txt
ckanext_metadata.egg-info/namespace_packages.txt
ckanext_metadata.egg-info/top_level.txt