Metadata-Version: 1.1
Name: ckanext-metadata
Version: 0.0.2
Summary: Metadata DDW Satu Data Indonesia
Home-page: https://github.com/ericsnth/ckanext-metadata
Author: Ericson Thomas
Author-email: ericsn.th@gmail.com
License: Apache License 2.0
Keywords: CKAN metadata SDI
Platform: UNKNOWN
Classifier: Development Status :: 5 - Production/Stable
Classifier: Programming Language :: Python
Classifier: Programming Language :: Python :: 2.7
Classifier: Topic :: Software Development :: Libraries
